isa_model/__init__.py
isa_model/client.py
isa_model/inference_client.py
isa_model/core/config.py
isa_model/core/dependencies.py
isa_model/core/pricing_manager.py
isa_model/core/types.py
isa_model/core/cache/redis_cache.py
isa_model/core/config/__init__.py
isa_model/core/config/config_manager.py
isa_model/core/config/environments/development.yaml
isa_model/core/config/environments/production.yaml
isa_model/core/config/providers/cerebras_models.yaml
isa_model/core/config/providers/isa_models.yaml
isa_model/core/config/providers/ollama_models.yaml
isa_model/core/config/providers/openai_models.yaml
isa_model/core/config/providers/replicate_models.yaml
isa_model/core/config/providers/yyds_models.yaml
isa_model/core/database/__init__.py
isa_model/core/database/direct_db_client.py
isa_model/core/database/migration_manager.py
isa_model/core/database/migrations.py
isa_model/core/database/supabase_client.py
isa_model/core/discovery/__init__.py
isa_model/core/discovery/consul_discovery.py
isa_model/core/logging/__init__.py
isa_model/core/logging/inference_logger.py
isa_model/core/logging/loki_logger.py
isa_model/core/models/__init__.py
isa_model/core/models/config_models.py
isa_model/core/models/deployment_billing_tracker.py
isa_model/core/models/model_billing_tracker.py
isa_model/core/models/model_manager.py
isa_model/core/models/model_metadata.py
isa_model/core/models/model_repo.py
isa_model/core/models/model_statistics_tracker.py
isa_model/core/models/model_storage.py
isa_model/core/models/model_version_manager.py
isa_model/core/models/system_models.py
isa_model/core/repositories/__init__.py
isa_model/core/repositories/config_repository.py
isa_model/core/resilience/circuit_breaker.py
isa_model/core/services/__init__.py
isa_model/core/services/intelligent_model_selector.py
isa_model/core/storage/local_storage.py
isa_model/deployment/__init__.py
isa_model/deployment/core/__init__.py
isa_model/deployment/core/deployment_manager.py
isa_model/deployment/modal/__init__.py
isa_model-0.5.4.dist-info/METADATA
isa_model-0.5.4.dist-info/WHEEL
isa_model-0.5.4.dist-info/top_level.txt
isa_model-0.5.4.dist-info/RECORD
