Metadata-Version: 2.4
Name: isa_model
Version: 0.5.4
Summary: Unified AI model serving framework with API streaming support
Author: isA_Model Contributors
Classifier: Development Status :: 3 - Alpha
Classifier: Intended Audience :: Developers
Classifier: Operating System :: OS Independent
Classifier: Programming Language :: Python :: 3
Requires-Python: >=3.8
Requires-Dist: fastapi>=0.95.0
Requires-Dist: uvicorn>=0.22.0
Requires-Dist: pydantic>=2.0.0
Requires-Dist: httpx>=0.23.0
Requires-Dist: requests>=2.28.0
Requires-Dist: aiohttp>=3.8.0
Requires-Dist: python-dotenv>=1.0.0
Requires-Dist: numpy>=1.20.0
Requires-Dist: supabase>=2.0.0
Requires-Dist: psycopg2-binary>=2.9.0
Requires-Dist: asyncpg>=0.28.0
Requires-Dist: slowapi>=0.1.8
Requires-Dist: circuitbreaker>=1.3.2
Requires-Dist: structlog>=23.1.0
Requires-Dist: psutil>=5.9.0
Requires-Dist: redis>=4.5.0
Requires-Dist: tenacity>=8.2.0
Provides-Extra: cloud
Requires-Dist: openai>=1.10.0; extra == "cloud"
Requires-Dist: replicate>=0.23.0; extra == "cloud"
Requires-Dist: cerebras-cloud-sdk>=1.0.0; extra == "cloud"
Requires-Dist: modal>=0.63.0; extra == "cloud"
Requires-Dist: grpclib>=0.4.7; extra == "cloud"
Requires-Dist: python-logging-loki>=0.3.1; extra == "cloud"
Requires-Dist: huggingface-hub>=0.16.0; extra == "cloud"
Requires-Dist: docker>=6.0.0; extra == "cloud"
Requires-Dist: influxdb-client>=1.36.0; extra == "cloud"
Requires-Dist: tiktoken>=0.5.0; extra == "cloud"
Provides-Extra: local
Requires-Dist: torch>=2.0.0; extra == "local"
Requires-Dist: transformers>=4.30.0; extra == "local"
Requires-Dist: accelerate>=0.20.0; extra == "local"
Requires-Dist: huggingface-hub>=0.16.0; extra == "local"
Requires-Dist: safetensors>=0.4.1; extra == "local"
Requires-Dist: sentencepiece>=0.1.99; extra == "local"
Provides-Extra: training
Requires-Dist: datasets>=2.10.0; extra == "training"
Requires-Dist: peft>=0.4.0; extra == "training"
Requires-Dist: trl>=0.4.0; extra == "training"
Requires-Dist: bitsandbytes>=0.39.0; extra == "training"
Provides-Extra: audio
Requires-Dist: librosa>=0.10.1; extra == "audio"
Requires-Dist: soundfile>=0.12.1; extra == "audio"
Requires-Dist: numba>=0.57.0; extra == "audio"
Provides-Extra: vision
Requires-Dist: Pillow>=10.0.1; extra == "vision"
Requires-Dist: torchvision>=0.15.2; extra == "vision"
Provides-Extra: langchain
Requires-Dist: langchain-core>=0.1.0; extra == "langchain"
Requires-Dist: langchain-openai>=0.0.2; extra == "langchain"
Provides-Extra: storage
Requires-Dist: boto3>=1.26.0; extra == "storage"
Requires-Dist: google-cloud-storage>=2.7.0; extra == "storage"
Provides-Extra: monitoring
Requires-Dist: mlflow>=2.4.0; extra == "monitoring"
Requires-Dist: redis>=4.5.0; extra == "monitoring"
Requires-Dist: prometheus-fastapi-instrumentator>=6.1.0; extra == "monitoring"
Requires-Dist: influxdb-client>=1.36.0; extra == "monitoring"
Requires-Dist: pgvector>=0.2.0; extra == "monitoring"
Requires-Dist: python-logging-loki>=0.3.1; extra == "monitoring"
Provides-Extra: k8s
Requires-Dist: kubernetes>=25.3.0; extra == "k8s"
Provides-Extra: gpu-cloud
Requires-Dist: runpod>=1.0.0; extra == "gpu-cloud"
Requires-Dist: ollama>=0.3.0; extra == "gpu-cloud"
Provides-Extra: dev
Requires-Dist: pytest>=7.0.0; extra == "dev"
Requires-Dist: black>=22.0.0; extra == "dev"
Requires-Dist: flake8>=4.0.0; extra == "dev"
Requires-Dist: mypy>=0.991; extra == "dev"
Requires-Dist: twine>=4.0.0; extra == "dev"
Provides-Extra: api-only
Requires-Dist: isa-model[cloud,langchain]; extra == "api-only"
Provides-Extra: full-local
Requires-Dist: isa-model[audio,langchain,local,training,vision]; extra == "full-local"
Provides-Extra: production
Requires-Dist: isa-model[cloud,k8s,monitoring,storage]; extra == "production"
Provides-Extra: staging
Requires-Dist: isa-model[cloud,langchain,monitoring,storage]; extra == "staging"
Requires-Dist: python-consul>=1.1.0; extra == "staging"
Provides-Extra: staging-minimal
Requires-Dist: isa-model[cloud,langchain,storage]; extra == "staging-minimal"
Requires-Dist: influxdb-client>=1.36.0; extra == "staging-minimal"
Requires-Dist: python-logging-loki>=0.3.1; extra == "staging-minimal"
Requires-Dist: python-consul>=1.1.0; extra == "staging-minimal"
Provides-Extra: all
Requires-Dist: isa-model[audio,cloud,gpu-cloud,k8s,langchain,local,monitoring,storage,training,vision]; extra == "all"
